ax_devil_rtsp/__init__.py
ax_devil_rtsp/deps.py
ax_devil_rtsp/logging.py
ax_devil_rtsp/rtsp_data_retrievers.py
ax_devil_rtsp/utils.py
ax_devil_rtsp/cli/__init__.py
ax_devil_rtsp/cli/__main__.py
ax_devil_rtsp/cli/main.py
ax_devil_rtsp/gstreamer/__init__.py
ax_devil_rtsp/gstreamer/callbacks.py
ax_devil_rtsp/gstreamer/client.py
ax_devil_rtsp/gstreamer/diagnostics.py
ax_devil_rtsp/gstreamer/pipeline.py
ax_devil_rtsp/gstreamer/utils.py
ax_devil_rtsp/raw_socket/metadata_raw.py
ax_devil_rtsp/setup_workarounds/__init__.py
ax_devil_rtsp/setup_workarounds/libproxy_segfault.py
ax_devil_rtsp-0.1.0.dist-info/licenses/LICENSE
ax_devil_rtsp-0.1.0.dist-info/METADATA
ax_devil_rtsp-0.1.0.dist-info/WHEEL
ax_devil_rtsp-0.1.0.dist-info/entry_points.txt
ax_devil_rtsp-0.1.0.dist-info/top_level.txt
ax_devil_rtsp-0.1.0.dist-info/RECORD
