Metadata-Version: 2.4
Name: ax-devil-rtsp
Version: 0.1.0
Summary: Python library for RTSP streaming from Axis devices
Author-email: Rasmus Rynell <Rynell.Rasmus@gmail.com>
License: MIT
Project-URL: Homepage, https://github.com/rasmusrynell/ax-devil-rtsp
Project-URL: Repository, https://github.com/rasmusrynell/ax-devil-rtsp.git
Project-URL: Documentation, https://github.com/rasmusrynell/ax-devil-rtsp#readme
Project-URL: Bug Tracker, https://github.com/rasmusrynell/ax-devil-rtsp/issues
Requires-Python: >=3.10
License-File: LICENSE
Requires-Dist: numpy>=1.20.0
Requires-Dist: opencv-python>=4.5.0
Requires-Dist: click>=8.0.0
Requires-Dist: rich>=13.9.4
Requires-Dist: urllib3>=2.5.0
Provides-Extra: dev
Requires-Dist: pytest>=7.0; extra == "dev"
Requires-Dist: pytest-asyncio; extra == "dev"
Requires-Dist: pytest-cov; extra == "dev"
Requires-Dist: black; extra == "dev"
Requires-Dist: ruff; extra == "dev"
Requires-Dist: opencv-python>=4.5.0; extra == "dev"
Dynamic: license-file
